{
  "name": "Blightstep Pathway // Searstep Pathway",
  "oracle_id": "e580a229-e800-4746-9d37-c32fcef8de28",
  "type_line": "Land // Land",
  "color_identity": [
    "B",
    "R"
  ],
  "fetchable": false,
  "set": "khm",
  "collector_number": "252",
  "image": "https://cards.scryfall.io/normal/front/0/c/0ce39a19-f51d-4a35-ae80-5b82eb15fcff.jpg?1669839373",
  "scryfall_uri": "https://scryfall.com/card/khm/252/blightstep-pathway-searstep-pathway?utm_source=api",
  "uri": "https://scryfall.com/card/khm/252/blightstep-pathway-searstep-pathway?utm_source=api",
  "url": "https://scryfall.com/card/khm/252/blightstep-pathway-searstep-pathway?utm_source=api",
  "rulings_uri": "https://api.scryfall.com/cards/0ce39a19-f51d-4a35-ae80-5b82eb15fcff/rulings",
  "purchase_uris": {
    "tcgplayer": "https://partner.tcgplayer.com/c/4931599/1830156/21018?subId1=api&u=https%3A%2F%2Fwww.tcgplayer.com%2Fproduct%2F229209%3Fpage%3D1",
    "cardmarket": "https://www.cardmarket.com/en/Magic/Products?idProduct=527450&referrer=scryfall&utm_campaign=card_prices&utm_medium=text&utm_source=scryfall",
    "cardhoarder": "https://www.cardhoarder.com/cards/87849?affiliate_id=scryfall&ref=card-profile&utm_campaign=affiliate&utm_medium=card&utm_source=scryfall"
  },
  "prices": {
    "latest": 5.35,
    "lowest": 5.33,
    "usd": "5.35",
    "usd_foil": "5.33"
  },
  "prints_uri": "https://api.scryfall.com/cards/search?order=released&q=oracleid%3Ae580a229-e800-4746-9d37-c32fcef8de28&unique=prints",
  "prints": [
    {
      "set": "slu",
      "set_name": "Secret Lair: Ultimate Edition",
      "collector_number": "12",
      "prices": {
        "usd": null,
        "usd_foil": "9.36",
        "usd_etched": null,
        "eur": null,
        "eur_foil": "6.65",
        "tix": null
      },
      "released_at": "2021-03-05"
    },
    {
      "set": "prm",
      "set_name": "Magic Online Promos",
      "collector_number": "88402",
      "prices": {
        "usd": null,
        "usd_foil": null,
        "usd_etched": null,
        "eur": null,
        "eur_foil": null,
        "tix": "1.30"
      },
      "released_at": "2021-02-28"
    },
    {
      "set": "pkhm",
      "set_name": "Kaldheim Promos",
      "collector_number": "252s",
      "prices": {
        "usd": null,
        "usd_foil": "6.03",
        "usd_etched": null,
        "eur": null,
        "eur_foil": "6.31",
        "tix": null
      },
      "released_at": "2021-02-05"
    },
    {
      "set": "khm",
      "set_name": "Kaldheim",
      "collector_number": "291",
      "prices": {
        "usd": "5.49",
        "usd_foil": "6.45",
        "usd_etched": null,
        "eur": "6.19",
        "eur_foil": "8.11",
        "tix": null
      },
      "released_at": "2021-02-05"
    },
    {
      "set": "khm",
      "set_name": "Kaldheim",
      "collector_number": "252",
      "prices": {
        "usd": "5.35",
        "usd_foil": "5.33",
        "usd_etched": null,
        "eur": "5.20",
        "eur_foil": "6.27",
        "tix": "0.26"
      },
      "released_at": "2021-02-05"
    },
    {
      "set": "plst",
      "set_name": "The List",
      "collector_number": "KHM-252",
      "prices": {
        "usd": "5.81",
        "usd_foil": null,
        "usd_etched": null,
        "eur": null,
        "eur_foil": null,
        "tix": null
      },
      "released_at": "2020-09-26"
    }
  ]
}