{
  "name": "Coalition Relic",
  "oracle_id": "008cb342-79f5-4df6-a6b7-0e9e22ed693f",
  "type_line": "Artifact",
  "color_identity": [],
  "fetchable": false,
  "set": "dmc",
  "collector_number": "180",
  "image": "https://cards.scryfall.io/normal/front/e/f/ef44324a-32bd-47e9-8fd9-258ba668de53.jpg?1673305762",
  "scryfall_uri": "https://scryfall.com/card/dmc/180/coalition-relic?utm_source=api",
  "uri": "https://scryfall.com/card/dmc/180/coalition-relic?utm_source=api",
  "url": "https://scryfall.com/card/dmc/180/coalition-relic?utm_source=api",
  "rulings_uri": "https://api.scryfall.com/cards/ef44324a-32bd-47e9-8fd9-258ba668de53/rulings",
  "purchase_uris": {
    "tcgplayer": "https://partner.tcgplayer.com/c/4931599/1830156/21018?subId1=api&u=https%3A%2F%2Fwww.tcgplayer.com%2Fproduct%2F283026%3Fpage%3D1",
    "cardmarket": "https://www.cardmarket.com/en/Magic/Products?idProduct=672147&referrer=scryfall&utm_campaign=card_prices&utm_medium=text&utm_source=scryfall",
    "cardhoarder": "https://www.cardhoarder.com/cards/103250?affiliate_id=scryfall&ref=card-profile&utm_campaign=affiliate&utm_medium=card&utm_source=scryfall"
  },
  "prices": {
    "latest": 0.38,
    "lowest": 0.26,
    "usd": "0.38",
    "usd_foil": null
  },
  "prints_uri": "https://api.scryfall.com/cards/search?order=released&q=oracleid%3A008cb342-79f5-4df6-a6b7-0e9e22ed693f&unique=prints",
  "prints": [
    {
      "set": "plst",
      "set_name": "The List",
      "collector_number": "A25-223",
      "prices": {
        "usd": "0.29",
        "usd_foil": null,
        "usd_etched": null,
        "eur": null,
        "eur_foil": null,
        "tix": null
      },
      "released_at": "2024-08-02"
    },
    {
      "set": "m3c",
      "set_name": "Modern Horizons 3 Commander",
      "collector_number": "286",
      "prices": {
        "usd": "0.26",
        "usd_foil": null,
        "usd_etched": null,
        "eur": "0.24",
        "eur_foil": "1.49",
        "tix": "0.03"
      },
      "released_at": "2024-06-14"
    },
    {
      "set": "plst",
      "set_name": "The List",
      "collector_number": "FUT-161",
      "prices": {
        "usd": "0.60",
        "usd_foil": null,
        "usd_etched": null,
        "eur": null,
        "eur_foil": null,
        "tix": null
      },
      "released_at": "2022-09-09"
    },
    {
      "set": "dmc",
      "set_name": "Dominaria United Commander",
      "collector_number": "180",
      "prices": {
        "usd": "0.38",
        "usd_foil": null,
        "usd_etched": null,
        "eur": "0.41",
        "eur_foil": null,
        "tix": "0.15"
      },
      "released_at": "2022-09-09"
    },
    {
      "set": "tsr",
      "set_name": "Time Spiral Remastered",
      "collector_number": "266",
      "prices": {
        "usd": "0.33",
        "usd_foil": "1.18",
        "usd_etched": null,
        "eur": "0.41",
        "eur_foil": "1.19",
        "tix": "0.02"
      },
      "released_at": "2021-03-19"
    },
    {
      "set": "a25",
      "set_name": "Masters 25",
      "collector_number": "223",
      "prices": {
        "usd": "0.71",
        "usd_foil": "2.24",
        "usd_etched": null,
        "eur": "0.79",
        "eur_foil": "3.22",
        "tix": "0.02"
      },
      "released_at": "2018-03-16"
    },
    {
      "set": "dde",
      "set_name": "Duel Decks: Phyrexia vs. the Coalition",
      "collector_number": "54",
      "prices": {
        "usd": "0.37",
        "usd_foil": null,
        "usd_etched": null,
        "eur": "0.55",
        "eur_foil": null,
        "tix": "0.14"
      },
      "released_at": "2010-03-19"
    },
    {
      "set": "fut",
      "set_name": "Future Sight",
      "collector_number": "161",
      "prices": {
        "usd": "1.05",
        "usd_foil": "23.00",
        "usd_etched": null,
        "eur": "1.45",
        "eur_foil": "7.17",
        "tix": "0.02"
      },
      "released_at": "2007-05-04"
    }
  ]
}